<?xml version="1.0" encoding="UTF-8" standalone="no"?><Lugares><Lugar nombre="Aeropuerto"><Pistas><Pista contenido="Tomo un avion cuya ala estaba adornada con una bandera verde, blanca y roja."/><Pista contenido="Conocia el antiguo nombre de la capital, Tenoctitlan."/><Pista contenido="Estaba emocionado por ir a la nacion de los antiguos Aztecas"/></Pistas></Lugar><Lugar nombre="Puerto"><Pistas><Pista contenido="Estaba pensando en viajar a un pais que se hable espaniol."/><Pista contenido="Queria observar la frontera mas conocida del mundo"/><Pista contenido="Queria tomar un poco de un buen tequila"/></Pistas></Lugar><Lugar nombre="Banco"><Pistas><Pista contenido="Dijo que iba a montar en caballo con el presidente."/><Pista contenido="Queria cambiar su dinero a peso mexicano"/><Pista contenido="Queria oir una serenata"/></Pistas></Lugar><Lugar nombre="Bolsa"><Pistas><Pista contenido="Vino a cambiar su dinero a pesos."/><Pista contenido="Queria saber el precio de la cania de azucar."/><Pista contenido="Quiso invertir en la televisacion del futbol"/></Pistas></Lugar><Lugar nombre="Biblioteca"><Pistas><Pista contenido="Dijo que queria averiguar sobre los Aztecas."/><Pista contenido="Investigaba los origenes de los calendarios mayas."/><Pista contenido="Llevaba un diccionario de espaniol"/></Pistas></Lugar></Lugares>