<?xml version="1.0" encoding="UTF-8" standalone="no"?><Lugares><Lugar nombre="Aeropuerto"><Pistas><Pista contenido="Paneo viajar hacia el medio oriente."/><Pista contenido="Pidio el asiento de al lado de la ventana para poder ver el Burj Khalifa."/><Pista contenido=""/></Pistas></Lugar><Lugar nombre="Puerto"><Pistas><Pista contenido="Se fue en un vehiculo que llevaba una bandera roja, verde, blanca y negra."/><Pista contenido="Deseaba viajar a la ciudad mas rica del planeta."/><Pista contenido=""/></Pistas></Lugar><Lugar nombre="Banco"><Pistas><Pista contenido="Cambio su dinero a dirham."/><Pista contenido="Queria conocer el valor del petroleo."/><Pista contenido=""/></Pistas></Lugar><Lugar nombre="Bolsa"><Pistas><Pista contenido="Dijo que iba a invertir en la industria del petroleo."/><Pista contenido="Iba a charlar con el jeque de negocios. "/><Pista contenido=""/></Pistas></Lugar><Lugar nombre="Biblioteca"><Pistas><Pista contenido="Estaba interesado en conocer el medio oriente."/><Pista contenido="Pregunto sobre la industria petrolera."/><Pista contenido="Queria conocer la isla e forma de palmera."/></Pistas></Lugar></Lugares>