<?xml version="1.0" encoding="UTF-8" standalone="no"?><Lugares><Lugar nombre="Aeropuerto"><Pistas><Pista contenido="Tomo un avion que llevaba una bandera azul, amarilla y verde."/><Pista contenido="Viajo a la capital de Ruanda."/><Pista contenido=""/></Pistas></Lugar><Lugar nombre="Puerto"><Pistas><Pista contenido="Se fue en un vehiculo que llevaba una bandera azul, amarilla y verde."/><Pista contenido="Se inquieto al saber que habia cocodrilos en el rio Kagera."/><Pista contenido=""/></Pistas></Lugar><Lugar nombre="Banco"><Pistas><Pista contenido="Pregunto a cuanto estaba el franco CFA."/><Pista contenido="Estaba haciendo investigaciones sobre personas extremadamente altas."/><Pista contenido=""/></Pistas></Lugar><Lugar nombre="Bolsa"><Pistas><Pista contenido="Compro francos CFA en el mercado negro."/><Pista contenido="Llevaba un diccionario en frances."/><Pista contenido=""/></Pistas></Lugar><Lugar nombre="Biblioteca"><Pistas><Pista contenido="Retiro libros sobre los gorilas de las montanias."/><Pista contenido="Dijo que queria averiguar sobre volcanes."/><Pista contenido="Dijo que queria averiguar sobre los mambos negros."/></Pistas></Lugar></Lugares>